autosort/__init__.py
autosort/config.py
autosort/formatting.py
autosort/parsing.py
autosort/sorting.py
autosort/utils.py
autosort-0.1.0.dist-info/metadata.json
autosort-0.1.0.dist-info/top_level.txt
autosort-0.1.0.dist-info/WHEEL
autosort-0.1.0.dist-info/METADATA
autosort-0.1.0.dist-info/RECORD
autosort-0.1.0.dist-info/DESCRIPTION.rst
