Metadata-Version: 2.0
Name: autosort
Version: 0.1.0
Summary: Automatically sort import statements.
Home-page: https://github.com/fbergroth/autosort
Author: Fredrik Bergroth
Author-email: fbergroth@gmail.com
License: MIT
Platform: UNKNOWN
